postgrest_py/__init__.py
postgrest_py/_async/__init__.py
postgrest_py/_async/client.py
postgrest_py/_async/request_builder.py
postgrest_py/_sync/__init__.py
postgrest_py/_sync/client.py
postgrest_py/_sync/request_builder.py
postgrest_py/base_client.py
postgrest_py/base_request_builder.py
postgrest_py/deprecated_client.py
postgrest_py/deprecated_get_request_builder.py
postgrest_py/exceptions.py
postgrest_py/types.py
postgrest_py/utils.py
postgrest_py-0.10.1.dist-info/LICENSE
postgrest_py-0.10.1.dist-info/WHEEL
postgrest_py-0.10.1.dist-info/METADATA
postgrest_py-0.10.1.dist-info/RECORD
