Metadata-Version: 2.1
Name: postgrest-py
Version: 0.10.1
Summary: PostgREST client for Python. This library provides an ORM interface to PostgREST.
Home-page: https://github.com/supabase/postgrest-py
License: MIT
Author: Lương Quang Mạnh
Author-email: luongquangmanh85@gmail.com
Requires-Python: >=3.7,<4.0
Classifier: License :: OSI Approved :: MIT License
Classifier: Operating System :: OS Independent
Classifier: Programming Language :: Python :: 3
Classifier: Programming Language :: Python :: 3.10
Classifier: Programming Language :: Python :: 3.7
Classifier: Programming Language :: Python :: 3.8
Classifier: Programming Language :: Python :: 3.9
Requires-Dist: deprecation (>=2.1.0,<3.0.0)
Requires-Dist: httpx (>=0.20,<0.23)
Requires-Dist: pydantic (>=1.9.0,<2.0.0)
Project-URL: Documentation, https://github.com/supabase/postgrest-py
Project-URL: Repository, https://github.com/supabase/postgrest-py
